[
  { "id": "MO-ART/P", "institution": "Morris", "name": "Artistic Performance" },
  { "id": "MO-HUM", "institution": "Morris", "name": "Communication, Language, Literature, and Philosophy" },
  { "id": "MO-E/CR", "institution": "Morris", "name": "Ethical and Civic Responsibility" },
  { "id": "MO-FA", "institution": "Morris", "name": "Fine Arts" },
  { "id": "MO-FL", "institution": "Morris", "name": "Foreign Language" },
  { "id": "MO-HIST", "institution": "Morris", "name": "Historical Perspectives" },
  { "id": "MO-SS", "institution": "Morris", "name": "Human Behavior, Social Processes, and Institutions" },
  { "id": "MO-HDIV", "institution": "Morris", "name": "Human Diversity" },
  { "id": "MO-IC", "institution": "Morris", "name": "Intellectual Community" },
  { "id": "MO-IP", "institution": "Morris", "name": "International Perspectives" },
  { "id": "MO-M/SR", "institution": "Morris", "name": "Mathematical/Symbolic Reasoning" },
  { "id": "MO-ENVT", "institution": "Morris", "name": "People and the Environment" },
  { "id": "MO-SCI-L", "institution": "Morris", "name": "Physical and Biological Sciences with Lab" },
  { "id": "MO-SCI", "institution": "Morris", "name": "Physical and Biological Sciences without Lab" },
  { "id": "MO-WLA", "institution": "Morris", "name": "Writing for the Liberal Arts" }
]